setup.py
mesa/__init__.py
mesa/base.py
mesa/pipeline.py
mesa/utils.py
mesa_toolkit.egg-info/PKG-INFO
mesa_toolkit.egg-info/SOURCES.txt
mesa_toolkit.egg-info/dependency_links.txt
mesa_toolkit.egg-info/not-zip-safe
mesa_toolkit.egg-info/top_level.txt
test/test_base.py