Metadata-Version: 1.0
Name: mesa-toolkit
Version: 0.2.1
Summary: dynamic toolkit for creating self-patching python apps
Home-page: http://github.com/rutherford/mesa
Author: Matt Rutherford
Author-email: rutherford@clientsideweb.net
License: BSD
Platform: UNKNOWN
